pypcad/api.py
pypcad/compat.py
pypcad/main.py
pypcad/port.py
pypcad/variant.py
pypcad-1.3.dist-info/METADATA
pypcad-1.3.dist-info/WHEEL
pypcad-1.3.dist-info/license.txt
pypcad-1.3.dist-info/top_level.txt
pypcad-1.3.dist-info/RECORD
