Metadata-Version: 2.1
Name: pypcad
Version: 1.3
Summary: Python API For ARES Commander And OEMs
Author: Graebert GmbH
License-File: license.txt
